pyfavicon/__init__.py
pyfavicon-0.1.1.dist-info/LICENSE
pyfavicon-0.1.1.dist-info/METADATA
pyfavicon-0.1.1.dist-info/WHEEL
pyfavicon-0.1.1.dist-info/top_level.txt
pyfavicon-0.1.1.dist-info/RECORD
