Metadata-Version: 2.1
Name: pyfavicon
Version: 0.1.1
Summary: Async favicon fetcher
Home-page: https://github.com/bilelmoussaoui/pyfavicon
Author: Bilal Elmoussaoui
Author-email: bil.elmoussaoui@gmail.com
License: MIT
Platform: UNKNOWN
Classifier: Intended Audience :: Developers
Classifier: Programming Language :: Python :: 3.7
Classifier: License :: OSI Approved :: MIT License
Classifier: Operating System :: OS Independent
Classifier: Topic :: Utilities
Classifier: Topic :: Internet :: WWW/HTTP
Requires-Dist: aiohttp
Requires-Dist: beautifulsoup4
Requires-Dist: Pillow
